encoder/priority_encoder.v
module encoder( input [7:0] in,
                output reg [2:0] out);

    always @(in) begin 
        casex(in) 
            8'b1xxxxxxx: out = 3'b111;
            8'b01xxxxxx: out = 3'b110;
            8'b001xxxxx: out = 3'b101;
            8'b0001xxxx: out = 3'b100;
            8'b00001xxx: out = 3'b011; 
            8'b000001xx: out = 3'b010;
            8'b0000001x: out = 3'b001; 
            8'b00000001: out = 3'b000;

            default: out = 3'b000;
            
        endcase
    end
endmodule

encoder/priority_tb.v
module priority_tb();
 
reg [7:0] in; 
wire [2:0] out;

integer i;

encoder p_encoder(  .in(in),
                    .out(out));
    
initial begin 

    $dumpfile("waveform.vcd");
    $dumpvars(0, priority_tb); 

    for(i=0; i<8; i=i+1) begin
        in = 8'b1 << i;
        #5;
        
        $display("in = %b => out = %b", in, out);
        
    end

    //test all low bits
    in = 8'b00000000; #5;
        $display ("in = %b => out = %b (should be 000)", in, out);
    
    //test multiple high bits
    in = 8'b01010101; #5;
        $display("in = %b, out = %b, (should be 110)", in, out);

    //random 
    repeat(5) begin 
        in = $random; 
        #5; 
        $display("in = %b ==> out = %b", in, out);
    end

    #5 $finish;
end
endmodule

encoder/waveform.vcd
$date
	Mon Jun  9 03:49:51 2025
$end
$version
	Icarus Verilog
$end
$timescale
	1s
$end
$scope module priority_tb $end
$var wire 3 ! out [2:0] $end
$var reg 8 " in [7:0] $end
$var integer 32 # i [31:0] $end
$scope module p_encoder $end
$var wire 8 $ in [7:0] $end
$var reg 3 % out [2:0] $end
$upscope $end
$upscope $end
$enddefinitions $end
$comment Show the parameter values. $end
$dumpall
$end
#0
$dumpvars
b0 %
b1 $
b0 #
b1 "
b0 !
$end
#5
b1 !
b1 %
b10 "
b10 $
b1 #
#10
b10 !
b10 %
b100 "
b100 $
b10 #
#15
b11 !
b11 %
b1000 "
b1000 $
b11 #
#20
b100 !
b100 %
b10000 "
b10000 $
b100 #
#25
b101 !
b101 %
b100000 "
b100000 $
b101 #
#30
b110 !
b110 %
b1000000 "
b1000000 $
b110 #
#35
b111 !
b111 %
b10000000 "
b10000000 $
b111 #
#40
b0 !
b0 %
b0 "
b0 $
b1000 #
#45
b110 !
b110 %
b1010101 "
b1010101 $
#50
b101 !
b101 %
b100100 "
b100100 $
#55
b111 !
b111 %
b10000001 "
b10000001 $
#60
b11 !
b11 %
b1001 "
b1001 $
#65
b110 !
b110 %
b1100011 "
b1100011 $
#70
b11 !
b11 %
b1101 "
b1101 $
